jupyflow/__init__.py
jupyflow/core.py
jupyflow-1.0.1.dist-info/METADATA
jupyflow-1.0.1.dist-info/WHEEL
jupyflow-1.0.1.dist-info/top_level.txt
jupyflow-1.0.1.dist-info/RECORD
