Metadata-Version: 2.4
Name: jupyflow
Version: 1.0.1
Summary: Split/rejoin Jupyter notebooks effortlessly.
Author: MiGan
Author-email: nyan_mikan@outlook.com
License: MIT
Project-URL: Homepage, https://github.com/yourname/jupyflow
Classifier: Programming Language :: Python :: 3
Classifier: License :: OSI Approved :: MIT License
Classifier: Operating System :: OS Independent
Requires-Python: >=3.7
Dynamic: author-email
Dynamic: requires-python
